SoloPy/CanInterface.py
SoloPy/Canable.py
SoloPy/ConstantCanopen.py
SoloPy/ConstantCommon.py
SoloPy/ConstantUart.py
SoloPy/Mcp2515.py
SoloPy/SOLOMotorControllers.py
SoloPy/SOLOMotorControllersCanopen.py
SoloPy/SOLOMotorControllersUart.py
SoloPy/SOLOMotorControllersUtils.py
SoloPy/__init__.py
solopy-4.0.0.dist-info/licenses/COPYING
solopy-4.0.0.dist-info/licenses/LICENSE.txt
solopy-4.0.0.dist-info/METADATA
solopy-4.0.0.dist-info/WHEEL
solopy-4.0.0.dist-info/top_level.txt
solopy-4.0.0.dist-info/RECORD
