Metadata-Version: 2.4
Name: SoloPy
Version: 4.0.0
Summary: Python library for interfacing with Solo Motor Controllers
Home-page: https://github.com/Solo-FL/SoloPy
Author: Solo
Author-email: support@solomotorcontrollers.com
License: MIT
Project-URL: Source, https://github.com/Solo-FL/SoloPy
Project-URL: Download, https://github.com/Solo-FL/SoloPy/archive/refs/tags/v4.0.0.tar.gz
Project-URL: Documentation, https://github.com/Solo-FL/SoloPy/wiki
Classifier: Development Status :: 4 - Beta
Classifier: Intended Audience :: Developers
Classifier: Topic :: Software Development :: Build Tools
Classifier: License :: OSI Approved :: MIT License
Classifier: Programming Language :: Python :: 3
Classifier: Programming Language :: Python :: 3.4
Classifier: Programming Language :: Python :: 3.5
Classifier: Programming Language :: Python :: 3.6
Classifier: Programming Language :: Python :: 3.7
Classifier: Programming Language :: Python :: 3.8
Classifier: Programming Language :: Python :: 3.9
Requires-Python: >=3.4
License-File: LICENSE.txt
License-File: COPYING
Requires-Dist: pyserial
Requires-Dist: python-can
Requires-Dist: python-interface
Dynamic: author
Dynamic: author-email
Dynamic: classifier
Dynamic: home-page
Dynamic: license
Dynamic: license-file
Dynamic: project-url
Dynamic: requires-dist
Dynamic: requires-python
Dynamic: summary
